{"noiseKey":{"private":{"type":"Buffer","data":"IFApXwBJII6AEmHSSAQjC8QV66O0B4p2vuVGUnx7J1A="},"public":{"type":"Buffer","data":"Ks4V9CaOTI9ulSQskuLie4e2fHWh5D7XhSpKiZfm0ww="}},"pairingEphemeralKeyPair":{"private":{"type":"Buffer","data":"SB1jrAe3henSSHy+ggP8vprEQc8pHs7L78WM3yUacUo="},"public":{"type":"Buffer","data":"x4ZdInn9fPkiGbhOXW9IkFWoz6ZqZEFZFc4AvYCeATk="}},"signedIdentityKey":{"private":{"type":"Buffer","data":"CDa9hPQT7cArUXFO21G24Jh544Gb/d+I2YD5sEupMnM="},"public":{"type":"Buffer","data":"shEs4r8SUSdeshbd4YMhdewO+mAi2Z9HiV3E8W4c2V8="}},"signedPreKey":{"keyPair":{"private":{"type":"Buffer","data":"+Px8FvXGO7ZNINXpzIW4rLOuCvgcMoSD03bvEkzXgEc="},"public":{"type":"Buffer","data":"/Rm6yDrI/4AsAjwxTqr1RXdNq0OzvRvjfjeNBzSuxzc="}},"signature":{"type":"Buffer","data":"uLgIP1kN8NnTQkLSJe4WQdBGyvf2AP7yLQWTrTtdQi/0Jmn3wh6vz+hk2RzJHTg/DhvxjIMDaASpmH2FGimjAQ=="},"keyId":1},"registrationId":103,"advSecretKey":"ReKY5Ana2fj3+xbW5l9RgXY2C4rChJd3fGP/HLyhy+s=","processedHistoryMessages":[{"key":{"remoteJid":"254743982206@s.whatsapp.net","fromMe":false,"id":"A58E80FF5522F4D1EAF7980D6B9F3955","participant":"","addressingMode":"pn"},"messageTimestamp":1762634915},{"key":{"remoteJid":"254743982206@s.whatsapp.net","fromMe":false,"id":"A5794F06573ABB1ECEB851813C096E5C","participant":"","addressingMode":"pn"},"messageTimestamp":1762634916},{"key":{"remoteJid":"254743982206@s.whatsapp.net","fromMe":false,"id":"A5AE922150A9F6D5257944CB48191109","participant":"","addressingMode":"pn"},"messageTimestamp":1762634919},{"key":{"remoteJid":"254743982206@s.whatsapp.net","fromMe":false,"id":"A5A097435EDBF4517A71ACDF1EAD4A87","participant":"","addressingMode":"pn"},"messageTimestamp":1762634920},{"key":{"remoteJid":"254743982206@s.whatsapp.net","fromMe":false,"id":"A5B52EBDB8B05C329787319E4C89B3D0","participant":"","addressingMode":"pn"},"messageTimestamp":1762634947},{"key":{"remoteJid":"254743982206@s.whatsapp.net","fromMe":false,"id":"A55E328EED8F24B18ABFAA070360F715","participant":"","addressingMode":"pn"},"messageTimestamp":1762634961},{"key":{"remoteJid":"254743982206@s.whatsapp.net","fromMe":false,"id":"A533A1C1759B0415F19FEDB176F02E68","participant":"","addressingMode":"pn"},"messageTimestamp":1762634973},{"key":{"remoteJid":"254743982206@s.whatsapp.net","fromMe":false,"id":"A5681C62459D08CB5104587FB6E7431C","participant":"","addressingMode":"pn"},"messageTimestamp":1762634999},{"key":{"remoteJid":"254743982206@s.whatsapp.net","fromMe":false,"id":"A53C3EDA41D161DB7BDCCFB4472046DB","participant":"","addressingMode":"pn"},"messageTimestamp":1762635020},{"key":{"remoteJid":"254743982206@s.whatsapp.net","fromMe":false,"id":"A5489D27204CEE66B828DDC6F461D518","participant":"","addressingMode":"pn"},"messageTimestamp":1762635048},{"key":{"remoteJid":"254743982206@s.whatsapp.net","fromMe":false,"id":"A5004C73C6086C4FA5418444AF51C165","participant":"","addressingMode":"pn"},"messageTimestamp":1762635123},{"key":{"remoteJid":"254743982206@s.whatsapp.net","fromMe":false,"id":"A5810F9E65412A30B65451BE32CF5CBA","participant":"","addressingMode":"pn"},"messageTimestamp":1762635134},{"key":{"remoteJid":"254743982206@s.whatsapp.net","fromMe":false,"id":"A5F059C814D74D62C78F93B2AFC51959","participant":"","addressingMode":"pn"},"messageTimestamp":1762635151},{"key":{"remoteJid":"254743982206@s.whatsapp.net","fromMe":false,"id":"A5B94579E35C7A9530347815363D44D9","participant":"","addressingMode":"pn"},"messageTimestamp":1762635151},{"key":{"remoteJid":"254743982206@s.whatsapp.net","fromMe":false,"id":"A5E97ED4DCEFDD79583F4DB990D8BB48","participant":"","addressingMode":"pn"},"messageTimestamp":1762635172},{"key":{"remoteJid":"254743982206@s.whatsapp.net","fromMe":false,"id":"A5FE47C05CA59D069E01DCDA58A4A085","participant":"","addressingMode":"pn"},"messageTimestamp":1762635208},{"key":{"remoteJid":"254743982206@s.whatsapp.net","fromMe":false,"id":"A541B448AEBE466B64E99BA412757FBF","participant":"","addressingMode":"pn"},"messageTimestamp":1762635229},{"key":{"remoteJid":"254743982206@s.whatsapp.net","fromMe":false,"id":"A5A0BA18977885168A88DCE24FEA7AA1","participant":"","addressingMode":"pn"},"messageTimestamp":1762635230},{"key":{"remoteJid":"254743982206@s.whatsapp.net","fromMe":false,"id":"A5FF630778B8A70442C1B49872F24594","participant":"","addressingMode":"pn"},"messageTimestamp":1762635230}],"nextPreKeyId":824,"firstUnuploadedPreKeyId":824,"accountSyncCounter":1,"accountSettings":{"unarchiveChats":false},"registered":true,"pairingCode":"Q7YMYVF8","me":{"id":"254743982206:11@s.whatsapp.net","name":"dev bera</>","lid":"260958337380428:11@lid"},"account":{"details":"COygqc4GEIPZvsgGGBIgACgA","accountSignatureKey":"dQitKDj6VIcILmTGf5U7gsnPt+44S/7QmRa2BWJJrDU=","accountSignature":"zabmXLac3wWbApOc+UF5yhAizMZ7MXlfBDgGsKKbreGPsjY7YwmX0qP4iB3gAxL9TY1/BNEAKyDhBm/Q9GQbAg==","deviceSignature":"90OFazWKSFeGO+TlbnMsfwGyzC7/Q9ggIa+Gvv4CcN8B2+MbutalMWHpqbfIfK+RzManre200Y0jiES4EJQyDw=="},"signalIdentities":[{"identifier":{"name":"260958337380428:11@lid","deviceId":0},"identifierKey":{"type":"Buffer","data":"BXUIrSg4+lSHCC5kxn+VO4LJz7fuOEv+0JkWtgViSaw1"}}],"platform":"smba","routingInfo":{"type":"Buffer","data":"CA0ICAgS"},"lastAccountSyncTimestamp":1762634903,"lastPropHash":"3R9Z39","myAppStateKeyId":"AAAAANpq"}